{
  "entry": "server.js",
  "files": {
    "5ac245d8cd4d299051bb.js": "5ac245d8cd4d299051bb.js",
    "849fabbc6fda69646d47.js": "849fabbc6fda69646d47.js",
    "c75a148bb8a11ea53b31.js": "c75a148bb8a11ea53b31.js",
    "ec122f9027ab3a80ccf5.js": "ec122f9027ab3a80ccf5.js",
    "f2a0345b2b041bc75936.js": "f2a0345b2b041bc75936.js",
    "server.js": "server.js"
  },
  "maps": {
    "5ac245d8cd4d299051bb.js": "5ac245d8cd4d299051bb.js.map",
    "849fabbc6fda69646d47.js": "849fabbc6fda69646d47.js.map",
    "c75a148bb8a11ea53b31.js": "c75a148bb8a11ea53b31.js.map",
    "ec122f9027ab3a80ccf5.js": "ec122f9027ab3a80ccf5.js.map",
    "f2a0345b2b041bc75936.js": "f2a0345b2b041bc75936.js.map",
    "server.js": "server.js.map"
  }
}